ensembleperturbation/__init__.py
ensembleperturbation/client/__init__.py
ensembleperturbation/client/combine_results.py
ensembleperturbation/client/make_storm_ensemble.py
ensembleperturbation/client/perturb_tracks.py
ensembleperturbation/client/plot_results.py
ensembleperturbation/parsing/__init__.py
ensembleperturbation/parsing/adcirc.py
ensembleperturbation/parsing/comparison.py
ensembleperturbation/parsing/schism.py
ensembleperturbation/parsing/utilities.py
ensembleperturbation/perturbation/__init__.py
ensembleperturbation/perturbation/atcf.py
ensembleperturbation/plotting/__init__.py
ensembleperturbation/plotting/gdal_dataset.py
ensembleperturbation/plotting/geometry.py
ensembleperturbation/plotting/map.py
ensembleperturbation/plotting/nodes.py
ensembleperturbation/plotting/perturbation.py
ensembleperturbation/plotting/surrogate.py
ensembleperturbation/plotting/taylor_diagram.py
ensembleperturbation/plotting/utilities.py
ensembleperturbation/uncertainty_quantification/__init__.py
ensembleperturbation/uncertainty_quantification/ensemble_array.py
ensembleperturbation/uncertainty_quantification/karhunen_loeve_expansion.py
ensembleperturbation/uncertainty_quantification/polynomial_chaos.py
ensembleperturbation/uncertainty_quantification/surrogate.py
ensembleperturbation/utilities.py
ensembleperturbation-1.4.2.dist-info/METADATA
ensembleperturbation-1.4.2.dist-info/WHEEL
ensembleperturbation-1.4.2.dist-info/entry_points.txt
ensembleperturbation-1.4.2.dist-info/licenses/LICENSE
ensembleperturbation-1.4.2.dist-info/RECORD
