Metadata-Version: 2.4
Name: ensembleperturbation
Version: 1.4.2
Summary: perturbation of coupled model input over a space of input variables
License: CC0-1.0
License-File: LICENSE
Author: Zach Burnett
Requires-Python: >=3.9,<4.0
Classifier: License :: CC0 1.0 Universal (CC0 1.0) Public Domain Dedication
Classifier: Programming Language :: Python :: 3
Classifier: Programming Language :: Python :: 3.9
Classifier: Programming Language :: Python :: 3.10
Classifier: Programming Language :: Python :: 3.11
Classifier: Programming Language :: Python :: 3.12
Classifier: Programming Language :: Python :: 3.13
Classifier: Programming Language :: Python :: 3.14
Provides-Extra: adcirc
Provides-Extra: development
Provides-Extra: documentation
Provides-Extra: plotting
Provides-Extra: testing
Requires-Dist: adcircpy (>=1.3) ; extra == "adcirc"
Requires-Dist: appdirs
Requires-Dist: beautifulsoup4
Requires-Dist: cartopy ; extra == "plotting" or extra == "documentation"
Requires-Dist: chaospy
Requires-Dist: cmocean ; extra == "plotting" or extra == "documentation"
Requires-Dist: coupledmodeldriver (>=1.5)
Requires-Dist: dask
Requires-Dist: dunamai ; extra == "documentation"
Requires-Dist: f90nml
Requires-Dist: fiona
Requires-Dist: geodatasets
Requires-Dist: geopandas
Requires-Dist: isort ; extra == "development"
Requires-Dist: m2r2 ; extra == "documentation"
Requires-Dist: matplotlib ; extra == "plotting" or extra == "documentation"
Requires-Dist: netcdf4
Requires-Dist: numpy
Requires-Dist: oitnb ; extra == "development"
Requires-Dist: pandas (>=1.5)
Requires-Dist: pint
Requires-Dist: pint-pandas
Requires-Dist: pyproj (>=2.6)
Requires-Dist: pytest ; extra == "testing"
Requires-Dist: pytest-cov ; extra == "testing"
Requires-Dist: pytest-timeout ; extra == "testing"
Requires-Dist: pytest-xdist ; extra == "testing"
Requires-Dist: python-dateutil
Requires-Dist: requests
Requires-Dist: scikit-learn
Requires-Dist: scipy
Requires-Dist: shapely
Requires-Dist: sphinx ; extra == "documentation"
Requires-Dist: sphinx-rtd-theme ; extra == "documentation"
Requires-Dist: sphinxcontrib-bibtex ; extra == "documentation"
Requires-Dist: sphinxcontrib-programoutput ; extra == "documentation"
Requires-Dist: stormevents (>=2.2.5,!=2.3.0,!=2.3.1)
Requires-Dist: typepigeon
Requires-Dist: wget ; extra == "testing"
Project-URL: Documentation, https://ensembleperturbation.readthedocs.io
Project-URL: Repository, https://github.com/noaa-ocs-modeling/EnsemblePerturbation.git
